text2math/__init__.py
text2math/raw2text.py
text2math/stopwords.json
text2math/text2tokens.py
text2math/tokens2numbers.py
text2math-0.0.8.dev1.dist-info/DESCRIPTION.rst
text2math-0.0.8.dev1.dist-info/METADATA
text2math-0.0.8.dev1.dist-info/RECORD
text2math-0.0.8.dev1.dist-info/WHEEL
text2math-0.0.8.dev1.dist-info/metadata.json
text2math-0.0.8.dev1.dist-info/top_level.txt
