Metadata-Version: 2.0
Name: text2math
Version: 0.0.8.dev1
Summary: Simple package for generating ngrams and bag of words representation from text.
Home-page: https://github.com/steven-cutting/text2math
Author: Steven Cutting
Author-email: steven.e.cutting@linux.com
License: GNU GPL v3+
Keywords: nlp text ngram ngrams
Platform: UNKNOWN
Classifier: Topic :: Scientific/Engineering :: Artificial Intelligence
Classifier: Topic :: Scientific/Engineering :: Information Analysis
Classifier: Topic :: Text Processing :: Linguistic
Classifier: Intended Audience :: Science/Research
Classifier: Operating System :: OS Independent
Classifier: Development Status :: 3 - Alpha
Classifier: Programming Language :: Python :: 2.7
Classifier: Programming Language :: Python :: 3.3
Classifier: Programming Language :: Python :: 3.4
Classifier: Programming Language :: Python :: 3.5
Classifier: License :: OSI Approved :: GNU General Public License v3 (GPLv3)
Classifier: Development Status :: 2 - Pre-Alpha
Requires-Dist: chardet (>=2.3.0)
Requires-Dist: ftfy (==4.4.2)
Requires-Dist: toolz (>=0.7.4)
Requires-Dist: unidecode (>=0.04.19)
Provides-Extra: dev
Requires-Dist: beautifulsoup4 (>=4.4.0); extra == 'dev'
Requires-Dist: cchardet (>=1.0.0); extra == 'dev'
Requires-Dist: cytoolz (>=0.7.3); extra == 'dev'
Requires-Dist: lxml (>=3.4.4); extra == 'dev'
Provides-Extra: extra
Requires-Dist: beautifulsoup4 (>=4.4.0); extra == 'extra'
Requires-Dist: lxml (>=3.4.4); extra == 'extra'
Provides-Extra: faster
Requires-Dist: cchardet (>=1.0.0); extra == 'faster'
Requires-Dist: cytoolz (>=0.7.3); extra == 'faster'
Provides-Extra: test
Requires-Dist: pytest (>=2.8.7); extra == 'test'
Requires-Dist: pytest-runner (>=2.6.2); extra == 'test'
